{
  "questions": [
    {
      "page1": {
        "name": "Text_Question1",
        "position": { "x": 0, "y": 144 },
        "scale": { "x": 1, "y": 1, "z": 1 },
        "text": "분위기가 어색해질 때,\n먼저 말을 꺼내는 편이다.",
        "fontName": "font7",
        "fontSize": 43,
        "fontColor": { "r": 1, "g": 1, "b": 1, "a": 1 },
        "alignment": 1
      },
      "page2": {
        "name": "Text_Question1",
        "position": { "x": 0, "y": 100 },
        "scale": { "x": 1, "y": 1, "z": 1 },
        "text": "분위기가 어색해질 때,\n먼저 말을 꺼내는 편이다.",
        "fontName": "font7",
        "fontSize": 37,
        "fontColor": { "r": 1, "g": 1, "b": 1, "a": 1 },
        "alignment": 1
      }
    },
    {
      "page1": {
        "name": "Text_Question2",
        "position": { "x": 0, "y": 144 },
        "scale": { "x": 1, "y": 1, "z": 1 },
        "text": "자주 보이는 작은 반응은,\n깊이 고민하지 않고 넘어가는 편이다.",
        "fontName": "font7",
        "fontSize": 43,
        "fontColor": { "r": 1, "g": 1, "b": 1, "a": 1 },
        "alignment": 1
      },
      "page2": {
        "name": "Text_Question2",
        "position": { "x": 0, "y": 100 },
        "scale": { "x": 1, "y": 1, "z": 1 },
        "text": "자주 보이는 작은 반응은,\n깊이 고민하지 않고 넘어가는 편이다.",
        "fontName": "font7",
        "fontSize": 37,
        "fontColor": { "r": 1, "g": 1, "b": 1, "a": 1 },
        "alignment": 1
      }
    },
    {
      "page1": {
        "name": "Text_Question3",
        "position": { "x": 0, "y": 144 },
        "scale": { "x": 1, "y": 1, "z": 1 },
        "text": "상대가 나에게 무엇인가를\n기대하면 부담감을 느낀다.",
        "fontName": "font7",
        "fontSize": 43,
        "fontColor": { "r": 1, "g": 1, "b": 1, "a": 1 },
        "alignment": 1
      },
      "page2": {
        "name": "Text_Question3",
        "position": { "x": 0, "y": 100 },
        "scale": { "x": 1, "y": 1, "z": 1 },
        "text": "상대가 나에게 무엇인가를\n기대하면 부담감을 느낀다.",
        "fontName": "font7",
        "fontSize": 37,
        "fontColor": { "r": 1, "g": 1, "b": 1, "a": 1 },
        "alignment": 1
      }
    },
    {
      "page1": {
        "name": "Text_Question4",
        "position": { "x": 0, "y": 144 },
        "scale": { "x": 1, "y": 1, "z": 1 },
        "text": "상대방의 컨디션을 보고\n말을 할지 말지 결정하는 편이다.",
        "fontName": "font7",
        "fontSize": 43,
        "fontColor": { "r": 1, "g": 1, "b": 1, "a": 1 },
        "alignment": 1
      },
      "page2": {
        "name": "Text_Question4",
        "position": { "x": 0, "y": 100 },
        "scale": { "x": 1, "y": 1, "z": 1 },
        "text": "상대방의 컨디션을 보고\n말을 할지 말지 결정하는 편이다.",
        "fontName": "font7",
        "fontSize": 37,
        "fontColor": { "r": 1, "g": 1, "b": 1, "a": 1 },
        "alignment": 1
      }
    },
    {
      "page1": {
        "name": "Text_Question5",
        "position": { "x": 0, "y": 144 },
        "scale": { "x": 1, "y": 1, "z": 1 },
        "text": "상대가 어딘가 어색해 보이면,\n쉽게 넘기지 못하는 편이다.",
        "fontName": "font7",
        "fontSize": 43,
        "fontColor": { "r": 1, "g": 1, "b": 1, "a": 1 },
        "alignment": 1
      },
      "page2": {
        "name": "Text_Question5",
        "position": { "x": 0, "y": 100 },
        "scale": { "x": 1, "y": 1, "z": 1 },
        "text": "상대가 어딘가 어색해 보이면,\n쉽게 넘기지 못하는 편이다.",
        "fontName": "font7",
        "fontSize": 37,
        "fontColor": { "r": 1, "g": 1, "b": 1, "a": 1 },
        "alignment": 1
      }
    },
    {
      "page1": {
        "name": "Text_Question6",
        "position": { "x": 0, "y": 144 },
        "scale": { "x": 1, "y": 1, "z": 1 },
        "text": "경험적으로 특정 상황에서는\n반응하지 않게 되는 편이다.",
        "fontName": "font7",
        "fontSize": 43,
        "fontColor": { "r": 1, "g": 1, "b": 1, "a": 1 },
        "alignment": 1
      },
      "page2": {
        "name": "Text_Question6",
        "position": { "x": 0, "y": 100 },
        "scale": { "x": 1, "y": 1, "z": 1 },
        "text": "경험적으로 특정 상황에서는\n반응하지 않게 되는 편이다.",
        "fontName": "font7",
        "fontSize": 37,
        "fontColor": { "r": 1, "g": 1, "b": 1, "a": 1 },
        "alignment": 1
      }
    },
    {
      "page1": {
        "name": "Text_Question7",
        "position": { "x": 0, "y": 144 },
        "scale": { "x": 1, "y": 1, "z": 1 },
        "text": "한 번 정한 행동은,\n상대의 반응이 달라도\n그대로 유지하는 편이다.",
        "fontName": "font7",
        "fontSize": 43,
        "fontColor": { "r": 1, "g": 1, "b": 1, "a": 1 },
        "alignment": 1
      },
      "page2": {
        "name": "Text_Question7",
        "position": { "x": 0, "y": 100 },
        "scale": { "x": 1, "y": 1, "z": 1 },
        "text": "한 번 정한 행동은,\n상대의 반응이 달라도\n그대로 유지하는 편이다.",
        "fontName": "font7",
        "fontSize": 37,
        "fontColor": { "r": 1, "g": 1, "b": 1, "a": 1 },
        "alignment": 1
      }
    },
    {
      "page1": {
        "name": "Text_Question8",
        "position": { "x": 0, "y": 144 },
        "scale": { "x": 1, "y": 1, "z": 1 },
        "text": "서로 너무 잘 아는 사이라서\n더 가감없이 감정을 표현할 때가 있다.",
        "fontName": "font7",
        "fontSize": 43,
        "fontColor": { "r": 1, "g": 1, "b": 1, "a": 1 },
        "alignment": 1
      },
      "page2": {
        "name": "Text_Question8",
        "position": { "x": 0, "y": 100 },
        "scale": { "x": 1, "y": 1, "z": 1 },
        "text": "서로 너무 잘 아는 사이라서\n더 가감없이 감정을 표현할 때가 있다.",
        "fontName": "font7",
        "fontSize": 37,
        "fontColor": { "r": 1, "g": 1, "b": 1, "a": 1 },
        "alignment": 1
      }
    },
    {
      "page1": {
        "name": "Text_Question9",
        "position": { "x": 0, "y": 144 },
        "scale": { "x": 1, "y": 1, "z": 1 },
        "text": "감정적인 반응이 계속 될것 같으면,\n대화를 멈추는 편이다.",
        "fontName": "font7",
        "fontSize": 43,
        "fontColor": { "r": 1, "g": 1, "b": 1, "a": 1 },
        "alignment": 1
      },
      "page2": {
        "name": "Text_Question9",
        "position": { "x": 0, "y": 100 },
        "scale": { "x": 1, "y": 1, "z": 1 },
        "text": "감정적인 반응이 계속 될것 같으면,\n대화를 멈추는 편이다.",
        "fontName": "font7",
        "fontSize": 37,
        "fontColor": { "r": 1, "g": 1, "b": 1, "a": 1 },
        "alignment": 1
      }
    },
    {
      "page1": {
        "name": "Text_Question10",
        "position": { "x": 0, "y": 144 },
        "scale": { "x": 1, "y": 1, "z": 1 },
        "text": "상대의 반응이 예상과 다르면,\n바로 반응하기보다\n잠시 멈추는 편이다.",
        "fontName": "font7",
        "fontSize": 43,
        "fontColor": { "r": 1, "g": 1, "b": 1, "a": 1 },
        "alignment": 1
      },
      "page2": {
        "name": "Text_Question10",
        "position": { "x": 0, "y": 100 },
        "scale": { "x": 1, "y": 1, "z": 1 },
        "text": "상대의 반응이 예상과 다르면,\n바로 반응하기보다 잠시 멈추는 편이다.",
        "fontName": "font7",
        "fontSize": 37,
        "fontColor": { "r": 1, "g": 1, "b": 1, "a": 1 },
        "alignment": 1
      }
    },
    {
      "page1": {
        "name": "Text_Question11",
        "position": { "x": 0, "y": 144 },
        "scale": { "x": 1, "y": 1, "z": 1 },
        "text": "대화할 때, 내 반응이\n과하지 않은지 종종 살피는 편이다.",
        "fontName": "font7",
        "fontSize": 43,
        "fontColor": { "r": 1, "g": 1, "b": 1, "a": 1 },
        "alignment": 1
      },
      "page2": {
        "name": "Text_Question11",
        "position": { "x": 0, "y": 100 },
        "scale": { "x": 1, "y": 1, "z": 1 },
        "text": "대화할 때, 내 반응이\n과하지 않은지 종종 살피는 편이다.",
        "fontName": "font7",
        "fontSize": 37,
        "fontColor": { "r": 1, "g": 1, "b": 1, "a": 1 },
        "alignment": 1
      }
    },
    {
      "page1": {
        "name": "Text_Question12",
        "position": { "x": 0, "y": 144 },
        "scale": { "x": 1, "y": 1, "z": 1 },
        "text": "관계에서 감정 대응이 잦아지면,\n금세 피곤해지는 편이다.",
        "fontName": "font7",
        "fontSize": 43,
        "fontColor": { "r": 1, "g": 1, "b": 1, "a": 1 },
        "alignment": 1
      },
      "page2": {
        "name": "Text_Question12",
        "position": { "x": 0, "y": 100 },
        "scale": { "x": 1, "y": 1, "z": 1 },
        "text": "관계에서 감정 대응이 잦아지면,\n금세 피곤해지는 편이다.",
        "fontName": "font7",
        "fontSize": 37,
        "fontColor": { "r": 1, "g": 1, "b": 1, "a": 1 },
        "alignment": 1
      }
    },
    {
      "page1": {
        "name": "Text_Question13",
        "position": { "x": 0, "y": 144 },
        "scale": { "x": 1, "y": 1, "z": 1 },
        "text": "상대의 기분 변화가 느껴지면\n내가 맞춰주는 편이다.",
        "fontName": "font7",
        "fontSize": 43,
        "fontColor": { "r": 1, "g": 1, "b": 1, "a": 1 },
        "alignment": 1
      },
      "page2": {
        "name": "Text_Question13",
        "position": { "x": 0, "y": 100 },
        "scale": { "x": 1, "y": 1, "z": 1 },
        "text": "상대의 기분 변화가 느껴지면\n내가 맞춰주는 편이다.",
        "fontName": "font7",
        "fontSize": 37,
        "fontColor": { "r": 1, "g": 1, "b": 1, "a": 1 },
        "alignment": 1
      }
    },
    {
      "page1": {
        "name": "Text_Question14",
        "position": { "x": 0, "y": 144 },
        "scale": { "x": 1, "y": 1, "z": 1 },
        "text": "상대가 먼저 말하지 않는\n분위기라면, 나도 먼저\n말을 꺼내지 않는 편이다.",
        "fontName": "font7",
        "fontSize": 43,
        "fontColor": { "r": 1, "g": 1, "b": 1, "a": 1 },
        "alignment": 1
      },
      "page2": {
        "name": "Text_Question14",
        "position": { "x": 0, "y": 100 },
        "scale": { "x": 1, "y": 1, "z": 1 },
        "text": "상대가 먼저 말하지 않는 분위기라면,\n나도 먼저 말을 꺼내지 않는 편이다.",
        "fontName": "font7",
        "fontSize": 37,
        "fontColor": { "r": 1, "g": 1, "b": 1, "a": 1 },
        "alignment": 1
      }
    },
    {
      "page1": {
        "name": "Text_Question15",
        "position": { "x": 0, "y": 144 },
        "scale": { "x": 1, "y": 1, "z": 1 },
        "text": "상대에게 어떻게 반응해야 할지\n막막하게 느낄 때가 있다.",
        "fontName": "font7",
        "fontSize": 43,
        "fontColor": { "r": 1, "g": 1, "b": 1, "a": 1 },
        "alignment": 1
      },
      "page2": {
        "name": "Text_Question15",
        "position": { "x": 0, "y": 100 },
        "scale": { "x": 1, "y": 1, "z": 1 },
        "text": "상대에게 어떻게 반응해야 할지\n막막하게 느낄 때가 있다.",
        "fontName": "font7",
        "fontSize": 37,
        "fontColor": { "r": 1, "g": 1, "b": 1, "a": 1 },
        "alignment": 1
      }
    },
    {
      "page1": {
        "name": "Text_Question16",
        "position": { "x": 0, "y": 144 },
        "scale": { "x": 1, "y": 1, "z": 1 },
        "text": "상대의 반응이 바로 보이지 않아도,\n믿고 기다리는 편이다.",
        "fontName": "font7",
        "fontSize": 43,
        "fontColor": { "r": 1, "g": 1, "b": 1, "a": 1 },
        "alignment": 1
      },
      "page2": {
        "name": "Text_Question16",
        "position": { "x": 0, "y": 100 },
        "scale": { "x": 1, "y": 1, "z": 1 },
        "text": "상대의 반응이 바로 보이지 않아도,\n믿고 기다리는 편이다.",
        "fontName": "font7",
        "fontSize": 37,
        "fontColor": { "r": 1, "g": 1, "b": 1, "a": 1 },
        "alignment": 1
      }
    },
    {
      "page1": {
        "name": "Text_Question17",
        "position": { "x": 0, "y": 144 },
        "scale": { "x": 1, "y": 1, "z": 1 },
        "text": "반응이 어떻게 돌아올지 예상되어,\n굳이 반응하지 않을 때가 있다.",
        "fontName": "font7",
        "fontSize": 43,
        "fontColor": { "r": 1, "g": 1, "b": 1, "a": 1 },
        "alignment": 1
      },
      "page2": {
        "name": "Text_Question17",
        "position": { "x": 0, "y": 100 },
        "scale": { "x": 1, "y": 1, "z": 1 },
        "text": "반응이 어떻게 돌아올지 예상되어,\n굳이 반응하지 않을 때가 있다.",
        "fontName": "font7",
        "fontSize": 37,
        "fontColor": { "r": 1, "g": 1, "b": 1, "a": 1 },
        "alignment": 1
      }
    },
    {
      "page1": {
        "name": "Text_Question18",
        "position": { "x": 0, "y": 144 },
        "scale": { "x": 1, "y": 1, "z": 1 },
        "text": "갈등 상황에서는 감정을\n가라앉힌 뒤 반응하는 편이다.",
        "fontName": "font7",
        "fontSize": 43,
        "fontColor": { "r": 1, "g": 1, "b": 1, "a": 1 },
        "alignment": 1
      },
      "page2": {
        "name": "Text_Question18",
        "position": { "x": 0, "y": 100 },
        "scale": { "x": 1, "y": 1, "z": 1 },
        "text": "갈등 상황에서는 감정을\n가라앉힌 뒤 반응하는 편이다.",
        "fontName": "font7",
        "fontSize": 37,
        "fontColor": { "r": 1, "g": 1, "b": 1, "a": 1 },
        "alignment": 1
      }
    },
    {
      "page1": {
        "name": "Text_Question19",
        "position": { "x": 0, "y": 144 },
        "scale": { "x": 1, "y": 1, "z": 1 },
        "text": "평소와 다른 상대의\n반응이 느껴지면, 말이나\n행동이 조심스러워진다.",
        "fontName": "font7",
        "fontSize": 43,
        "fontColor": { "r": 1, "g": 1, "b": 1, "a": 1 },
        "alignment": 1
      },
      "page2": {
        "name": "Text_Question19",
        "position": { "x": 0, "y": 100 },
        "scale": { "x": 1, "y": 1, "z": 1 },
        "text": "평소와 다른 상대의 반응이 느껴지면,\n말이나 행동이 조심스러워진다.",
        "fontName": "font7",
        "fontSize": 37,
        "fontColor": { "r": 1, "g": 1, "b": 1, "a": 1 },
        "alignment": 1
      }
    },
    {
      "page1": {
        "name": "Text_Question20",
        "position": { "x": 0, "y": 144 },
        "scale": { "x": 1, "y": 1, "z": 1 },
        "text": "감정적으로 여유가 없을 때는,\n먼저 반응하지 않으려는 편이다.",
        "fontName": "font7",
        "fontSize": 43,
        "fontColor": { "r": 1, "g": 1, "b": 1, "a": 1 },
        "alignment": 1
      },
      "page2": {
        "name": "Text_Question20",
        "position": { "x": 0, "y": 100 },
        "scale": { "x": 1, "y": 1, "z": 1 },
        "text": "감정적으로 여유가 없을 때는,\n먼저 반응하지 않으려는 편이다.",
        "fontName": "font7",
        "fontSize": 37,
        "fontColor": { "r": 1, "g": 1, "b": 1, "a": 1 },
        "alignment": 1
      }
    }
  ]
}